ip_country_scraper
