Metadata-Version: 2.1
Name: ip-country-scraper
Version: 1.0.1
Summary: Automation Library
Home-page: UNKNOWN
Author: DataKund
Author-email: datakund@gmail.com
License: Apache License 2.0
Keywords: A python library to scrape country of the ip link provided
Platform: UNKNOWN
